vnaddress_aws/__init__.py
vnaddress_aws/combined.py
vnaddress_aws/parser.py
vnaddress_aws/constants/__init__.py
vnaddress_aws/constants/error_dict.py
vnaddress_aws/constants/full_address_error_dict.py
vnaddress_aws/constants/single_vowels.py
vnaddress_aws/constants/standard_addresses.py
vnaddress_aws/constants/standard_single_names.py
vnaddress_aws/functions/__init__.py
vnaddress_aws/functions/utils.py
vnaddress_aws/functions/acronym_layer/__init__.py
vnaddress_aws/functions/acronym_layer/acronym_execute.py
vnaddress_aws/functions/acronym_layer/constants.py
vnaddress_aws/functions/crf_layer/__init__.py
vnaddress_aws/functions/crf_layer/constants.py
vnaddress_aws/functions/crf_layer/crf_execute.py
vnaddress_aws/functions/crf_layer/word2features.py
vnaddress_aws/functions/spell_correction_layer/__init__.py
vnaddress_aws/functions/spell_correction_layer/match_word.py
vnaddress_aws/models/finalized_model.sav
vnaddress_aws-1.0.5.2.data/data/vnaddress_aws/finalized_model.sav
vnaddress_aws-1.0.5.2.data/scripts/vnas_aws
vnaddress_aws-1.0.5.2.dist-info/licenses/LICENSE
vnaddress_aws-1.0.5.2.dist-info/METADATA
vnaddress_aws-1.0.5.2.dist-info/WHEEL
vnaddress_aws-1.0.5.2.dist-info/top_level.txt
vnaddress_aws-1.0.5.2.dist-info/RECORD
